snoopy/__init__.py
snoopy/__main__.py
snoopy/snoopy.py
snoopy/ssh_bridge.py
snoopy/build/GitHub-Mark-32px.png
snoopy/build/app.js
snoopy/build/favicon.ico
snoopy/build/favicon2.ico
snoopy/build/index.html
snoopy/build/main.css
snoopy/build/qc_summary_template.html
snoopy/build/bootstrap/css/bootstrap.min.css
snoopy/build/bootstrap/fonts/glyphicons-halflings-regular.eot
snoopy/build/bootstrap/fonts/glyphicons-halflings-regular.svg
snoopy/build/bootstrap/fonts/glyphicons-halflings-regular.ttf
snoopy/build/bootstrap/fonts/glyphicons-halflings-regular.woff
snoopy/build/bootstrap/fonts/glyphicons-halflings-regular.woff2
snoopy/build/bootstrap/fonts/icomoon.eot
snoopy/build/bootstrap/fonts/icomoon.svg
snoopy/build/bootstrap/fonts/icomoon.ttf
snoopy/build/bootstrap/fonts/icomoon.woff
snoopy/build/dalliance/build/dalliance-all.js
snoopy/build/dalliance/build/dalliance-all.js.map
snoopy/build/dalliance/build/worker-all.js
snoopy/build/dalliance/build/worker-all.js.map
snoopy/build/dalliance/css/bootstrap-scoped.css
snoopy/build/dalliance/css/bootstrap.css
snoopy/build/dalliance/css/dalliance-scoped.css
snoopy/build/dalliance/css/dalliance.css
snoopy/build/dalliance/css/font-awesome.min.css
snoopy/build/dalliance/fonts/FontAwesome.otf
snoopy/build/dalliance/fonts/fontawesome-webfont.eot
snoopy/build/dalliance/fonts/fontawesome-webfont.svg
snoopy/build/dalliance/fonts/fontawesome-webfont.ttf
snoopy/build/dalliance/fonts/fontawesome-webfont.woff
snoopy-0.4.7.dist-info/DESCRIPTION.rst
snoopy-0.4.7.dist-info/METADATA
snoopy-0.4.7.dist-info/RECORD
snoopy-0.4.7.dist-info/WHEEL
snoopy-0.4.7.dist-info/entry_points.txt
snoopy-0.4.7.dist-info/metadata.json
snoopy-0.4.7.dist-info/top_level.txt
