Metadata-Version: 2.0
Name: snoopy
Version: 0.4.7
Summary: Browser based quality control tool to expedite reviewing predicted variants in next generation sequencing files.
Home-page: https://github.com/wtsi-medical-genomics/snoopy
Author: Daniel Rice
Author-email: dr9@sanger.ac.uk
License: MIT
Keywords: quality control qc variants next generation sequencing bam cram
Platform: UNKNOWN
Classifier: Development Status :: 4 - Beta
Classifier: Intended Audience :: Science/Research
Classifier: Topic :: Scientific/Engineering :: Bio-Informatics
Classifier: License :: OSI Approved :: MIT License
Classifier: Operating System :: POSIX
Classifier: Operating System :: MacOS
Classifier: Environment :: Web Environment
Classifier: Programming Language :: Python :: 2
Classifier: Programming Language :: Python :: 2.6
Classifier: Programming Language :: Python :: 2.7
Classifier: Programming Language :: Python :: 3
Classifier: Programming Language :: Python :: 3.3
Classifier: Programming Language :: Python :: 3.4
Classifier: Programming Language :: Python :: 3.5
Requires-Dist: paramiko
Requires-Dist: tornado
